{
	"Actor": {
		"types": [
			"Human",
			"Humanoid",
			"Metanthrope",
			"Protagonist",
			"Animal",
			"MetaTherion",
			"Artificial",
			"Animated-Object",
			"Animated-Humanoid",
			"Vehicle"
		],
		"templates": {
			"physical": {
				"physical": {
					"movement": {
						"type": "number",
						"label": "Movement",
						"initial": 10,
						"additional": 20,
						"sprint": 50,
						"Buffs": {
							"fly": {
								"type": "boolean",
								"dtype": "Boolean",
								"label": "Fly",
								"value": false
							},
							"photokinetic": {
								"type": "boolean",
								"dtype": "Boolean",
								"label": "Photokinetic",
								"value": false
							},
							"walk-wall": {
								"type": "boolean",
								"dtype": "Boolean",
								"label": "Wall Walk",
								"value": false
							},
							"walk-wave": {
								"type": "boolean",
								"dtype": "Boolean",
								"label": "Wave Walk",
								"value": false
							},
							"walk-earth": {
								"type": "boolean",
								"dtype": "Boolean",
								"label": "Earth Walk",
								"value": false
							}
						},
						"Conditions": {
							"immobilized": {
								"type": "boolean",
								"dtype": "Boolean",
								"label": "Immobilized",
								"value": false
							},
							"knockdown": {
								"type": "boolean",
								"dtype": "Boolean",
								"label": "Knocked Down",
								"value": false
							}
						}
					},
					"size": {
						"type": "number",
						"label": "Size",
						"initial": 10,
						"Buffs": {
							"enlarged": {
								"type": "number",
								"label": "Enlarged",
								"value": 0
							}
						},
						"Conditions": {
							"shrunken": {
								"type": "number",
								"label": "Shrunken",
								"value": 0
							}
						}
					},
					"weight": {
						"type": "number",
						"label": "Weight",
						"initial": 10,
						"Buffs": {
							"lightened": {
								"type": "number",
								"label": "Lightened",
								"value": 0
							}
						},
						"Conditions": {
							"encumbered": {
								"type": "number",
								"label": "Encumbered",
								"value": 0
							}
						}
					},
					"speed": {
						"type": "number",
						"label": "Speed",
						"initial": 10,
						"Buffs": {
							"accelerated": {
								"type": "number",
								"label": "Accelerated",
								"value": 0
							}
						},
						"Conditions": {
							"slowed": {
								"type": "number",
								"label": "Slowed",
								"value": 0
							}
						}
					},
					"resistances": {
						"cosmic": {
							"type": "number",
							"label": "Cosmic",
							"initial": 0
						},
						"elemental": {
							"type": "number",
							"label": "Elemental",
							"initial": 0
						},
						"material": {
							"type": "number",
							"label": "Material",
							"initial": 0
						},
						"psychic": {
							"type": "number",
							"label": "Psychic",
							"initial": 0
						}
					},
					"immunities": {
						"type": "text",
						"dtype": "String",
						"label": "Immunities",
						"value": "none"
					},
					"detections": {
						"type": "text",
						"dtype": "String",
						"label": "Detections",
						"value": "none"
					},
					"shifts": {
						"type": "text",
						"dtype": "String",
						"label": "Shifts",
						"value": "none"
					},
					"cover": {
						"type": "number",
						"label": "Cover",
						"initial": 0,
						"value": 0,
						"max": 100
					},
					"Description": {
						"type": "text",
						"dtype": "String",
						"label": "Physical Description",
						"value": "Height, Weight, details about physical appearance, etc."
					}
				}
			},
			"vital": {
				"Vital": {
					"Experience": {
						"type": "number",
						"dtype": "Number",
						"Label": "Experience",
						"Total": "1000",
						"Spent": 0,
						"Manual": 0,
						"Stored": 0
					},
					"age": {
						"type": "number",
						"dtype": "Number",
						"label": "Age",
						"value": 25
					},
					"arc": {
						"type": "text",
						"dtype": "String",
						"label": "Arc",
						"value": "Your Arc"
					},
					"background": {
						"type": "text",
						"dtype": "String",
						"label": "Background",
						"value": "Your Background"
					},
					"Life": {
						"type": "number",
						"label": "Life",
						"Initial": 100,
						"value": 100,
						"max": 0
					},
					"Destiny": {
						"type": "number",
						"label": "Destiny",
						"value": 20,
						"max": 100
					}
				}
			},
			"characteristics": {
				"Characteristics": {
					"Body": {
						"Initial": 30,
						"Progressed": 5,
						"Base": 0,
						"Current": 0,
						"Buff": { "Name": "Hardened", "Current": 0 },
						"Condition": { "Name": "Burned", "Current": 0 },
						"CoreConditions": { "Bleeding": 1, "Asphyxiation": 0, "Diseased": 0, "Maimed": 0 },
						"Stats": {
							"Endurance": {
								"Initial": 30,
								"Progressed": 5,
								"Base": 0,
								"Current": 0,
								"Roll": 0,
								"Buff": { "Name": "Fortified", "Current": 0 },
								"Condition": { "Name": "Bone Injury", "Current": 0 }
							},
							"Power": {
								"Initial": 30,
								"Progressed": 5,
								"Base": 0,
								"Current": 0,
								"Roll": 0,
								"Buff": { "Name": "Empowered", "Current": 0 },
								"Condition": { "Name": "Muscle Injury", "Current": 0 }
							},
							"Reflexes": {
								"Initial": 30,
								"Progressed": 5,
								"Base": 0,
								"Current": 0,
								"Roll": 0,
								"Buff": { "Name": "Hastened", "Current": 0 },
								"Condition": { "Name": "Skin Injury", "Current": 0 }
							}
						}
					},
					"Mind": {
						"Initial": 30,
						"Progressed": 5,
						"Base": 0,
						"Current": 0,
						"Buff": { "Name": "Sharpened", "Current": 0 },
						"Condition": { "Name": "Disconnected", "Current": 0 },
						"CoreConditions": {
							"Fatigue": 0,
							"Hunger": 0,
							"Pain": 0,
							"Sense-Lost": 0
						},
						"Stats": {
							"Perception": {
								"Initial": 30,
								"Progressed": 5,
								"Base": 0,
								"Current": 0,
								"Roll": 0,
								"Buff": { "Name": "Alerted", "Current": 0 },
								"Condition": { "Name": "Disoriented", "Current": 0 }
							},
							"Manipulation": {
								"Initial": 30,
								"Progressed": 5,
								"Base": 0,
								"Current": 0,
								"Roll": 0,
								"Buff": { "Name": "Articulated", "Current": 0 },
								"Condition": { "Name": "Confused", "Current": 0 }
							},
							"Creativity": {
								"Initial": 30,
								"Progressed": 5,
								"Base": 0,
								"Current": 0,
								"Roll": 0,
								"Buff": { "Name": "Inspired", "Current": 0 },
								"Condition": { "Name": "Wobbly", "Current": 0 }
							}
						}
					},
					"Soul": {
						"Initial": 10,
						"Progressed": 0,
						"Base": 0,
						"Current": 0,
						"Buff": { "Name": "Enlightened", "Current": 0 },
						"Condition": { "Name": "Tormented", "Current": 0 },
						"CoreConditions": { "Amnesia": 0, "Probed": 0, "Infiltrated": 0, "Unconscious": 0 },
						"Stats": {
							"Willpower": {
								"Initial": 10,
								"Progressed": 0,
								"Base": 0,
								"Current": 0,
								"Roll": 0,
								"Buff": { "Name": "Determined", "Current": 0 },
								"Condition": { "Name": "Terrorized", "Current": 0 }
							},
							"Consciousness": {
								"Initial": 20,
								"Progressed": 0,
								"Base": 0,
								"Current": 0,
								"Roll": 0,
								"Buff": { "Name": "Awakened", "Current": 0 },
								"Condition": { "Name": "Demented", "Current": 0 }
							},
							"Awareness": {
								"Initial": 20,
								"Progressed": 0,
								"Base": 0,
								"Current": 0,
								"Roll": 0,
								"Buff": { "Name": "Focused", "Current": 0 },
								"Condition": { "Name": "Bewildered", "Current": 0 }
							}
						}
					}
				}
			},
			"humanoids": {
				"humanoids": {
					"hitbox": {
						"head": {
							"type": "number",
							"label": "Head",
							"weight": 5
						},
						"torso-upper": {
							"type": "number",
							"label": "Upper Torso",
							"weight": 15
						},
						"torso-lower": {
							"type": "number",
							"label": "Lower Torso",
							"weight": 10
						},
						"arm-left": {
							"type": "number",
							"label": "Left Arm",
							"weight": 15
						},
						"arm-right": {
							"type": "number",
							"label": "Right Arm",
							"weight": 15
						},
						"leg-left": {
							"type": "number",
							"label": "Left Leg",
							"weight": 20
						},
						"leg-right": {
							"type": "number",
							"label": "Right Leg",
							"weight": 20
						}
					},
					"origin": {
						"type": "text",
						"dtype": "String",
						"label": "Origin",
						"value": "Planet Earth"
					},
					"species": {
						"type": "text",
						"dtype": "String",
						"label": "Species",
						"value": "Human"
					},
					"gender": {
						"type": "text",
						"dtype": "String",
						"label": "Gender",
						"value": "Other"
					},
					"birthplace": {
						"type": "text",
						"dtype": "String",
						"label": "Birthplace",
						"value": "Random City"
					},
					"weight": {
						"type": "text",
						"dtype": "String",
						"label": "Weight",
						"value": "Your Weight"
					},
					"height": {
						"type": "text",
						"dtype": "String",
						"label": "Height",
						"value": "Your Height"
					},
					"Description": {
						"type": "text",
						"dtype": "String",
						"label": "Humanoid Description",
						"value": "A typical human with brown hair and brown eyes."
					}
				}
			},
			"perks": {
				"Perks": {
					"Knowledge": {
						"Academics": {
							"type": "number",
							"dtype": "Number",
							"label": "Academics",
							"value": 0
						},
						"Engineering": {
							"type": "number",
							"dtype": "Number",
							"label": "Engineering",
							"value": 0
						},
						"Medicine": {
							"type": "number",
							"dtype": "Number",
							"label": "Medicine",
							"value": 0
						},
						"Science": {
							"type": "number",
							"dtype": "Number",
							"label": "Science",
							"value": 0
						},
						"Lore": {
							"type": "number",
							"dtype": "Number",
							"label": "Lore",
							"value": 0
						}
					},
					"Skills": {
						"Artistry": {
							"type": "number",
							"dtype": "Number",
							"label": "Artistry",
							"value": 0
						},
						"Athletics": {
							"type": "number",
							"dtype": "Number",
							"label": "Athletics",
							"value": 0
						},
						"Expertise": {
							"type": "number",
							"dtype": "Number",
							"label": "Expertise",
							"value": 0
						},
						"Operation": {
							"type": "number",
							"dtype": "Number",
							"label": "Operation",
							"value": 0
						},
						"Weapons": {
							"type": "number",
							"dtype": "Number",
							"label": "Weapons",
							"value": 0
						}
					},
					"Details":{
						"Fields": {
							"type": "text",
							"dtype": "String",
							"label": "Fields of Study",
							"value": "Field 1, Field 2 etc."
						},
						"Expertise": {
							"type": "text",
							"dtype": "String",
							"label": "Expertise",
							"value": "Expertise 1, Expertise 2 etc."
						},
						"Languages": {
							"type": "text",
							"dtype": "String",
							"label": "Languages",
							"value": "Language 1, Language 2 etc."
						}
					}
				}
			},
			"animals": {
				"animals": {
					"hitbox": {
						"head": {
							"type": "number",
							"label": "Head",
							"weight": 5
						},
						"body-upper": {
							"type": "number",
							"label": "Upper Body",
							"weight": 15
						},
						"body-lower": {
							"type": "number",
							"label": "Lower Body",
							"weight": 10
						},
						"arm-left": {
							"type": "number",
							"label": "Left Arm",
							"weight": 10
						},
						"arm-right": {
							"type": "number",
							"label": "Right Arm",
							"weight": 10
						},
						"leg-left": {
							"type": "number",
							"label": "Left Leg",
							"weight": 10
						},
						"leg-right": {
							"type": "number",
							"label": "Right Leg",
							"weight": 10
						},
						"tail": {
							"type": "number",
							"label": "Tail",
							"weight": 10
						},
						"wing-left": {
							"type": "number",
							"label": "Left Wing",
							"weight": 10
						},
						"wing-right": {
							"type": "number",
							"label": "Right Wing",
							"weight": 10
						}
					},
					"details-animal": {
						"type": "text",
						"dtype": "String",
						"label": "Animal Details",
						"value": "some animal"
					}
				}
			},
			"synthetic": {
				"Synthetic": {
					"hitbox": {
						"head": {
							"type": "number",
							"label": "Head",
							"weight": 5
						},
						"torso-upper": {
							"type": "number",
							"label": "Upper Torso",
							"weight": 15
						},
						"torso-lower": {
							"type": "number",
							"label": "Lower Torso",
							"weight": 10
						},
						"arm-left": {
							"type": "number",
							"label": "Left Arm",
							"weight": 15
						},
						"arm-right": {
							"type": "number",
							"label": "Right Arm",
							"weight": 15
						},
						"leg-left": {
							"type": "number",
							"label": "Left Leg",
							"weight": 20
						},
						"leg-right": {
							"type": "number",
							"label": "Right Leg",
							"weight": 20
						}
					},
					"Life": {
						"type": "number",
						"label": "Durability",
						"value": 200,
						"max": 0
					},
					"Description": {
						"type": "text",
						"dtype": "String",
						"label": "Synthetic Description",
						"value": "some synthetic life form"
					}
				}
			},
			"entermeta": {
				"entermeta": {
					"metamorphosis": {
						"type": "text",
						"dtype": "String",
						"label": "Metamorphosis",
						"value": "some metamorphosis"
					},
					"regression": {
						"type": "text",
						"dtype": "String",
						"label": "Regression",
						"value": "Your Regression"
					},
					"primemetapower": {
						"type": "text",
						"dtype": "String",
						"label": "Prime Metapower",
						"value": "your Prime Metapower"
					},
					"sagas": {
						"type": "text",
						"dtype": "String",
						"label": "Sagas",
						"value": "Sagas you have participated in"
					},
					"coalition": {
						"type": "text",
						"dtype": "String",
						"label": "Coalition",
						"value": "Player coalition you are a member of"
					},
					"faction": {
						"type": "text",
						"dtype": "String",
						"label": "Faction",
						"value": "Faction Name"
					},
					"narrator": {
						"type": "text",
						"dtype": "String",
						"label": "Narrator",
						"value": "Narrator Name"
					},
					"Description": {
						"type": "text",
						"dtype": "String",
						"label": "Metamorphosis Details",
						"value": "some metamorphosis"
					}
				}
			}
		},
		"Human": {
			"templates": ["physical", "vital", "humanoids"],
			"metaowner": {
				"type": "text",
				"dtype": "String",
				"label": "Metaowner",
				"value": "NPC"
			}
		},
		"Humanoid": {
			"templates": ["physical", "vital", "characteristics", "humanoids", "perks"],
			"metaowner": {
				"type": "text",
				"dtype": "String",
				"label": "Metaowner",
				"value": "NPC"
			}
		},
		"Metanthrope": {
			"templates": ["physical", "vital", "characteristics", "humanoids", "perks", "entermeta"],
			"metaowner": {
				"type": "text",
				"dtype": "String",
				"label": "Metaowner",
				"value": "NPC"
			}
		},
		"Protagonist": {
			"templates": ["physical", "vital", "characteristics", "humanoids", "perks", "entermeta"],
			"metaowner": {
				"type": "text",
				"dtype": "String",
				"label": "Metaowner",
				"value": "Player"
			},
			"notes-protagonist": {
				"type": "text",
				"dtype": "String",
				"label": "Protagonist Notes",
				"value": "My Notes"
			},
			"notes-narrator": {
				"type": "text",
				"dtype": "String",
				"label": "Narrator Notes",
				"value": "This is my favorite Protagonist"
			}
		},
		"Animal": {
			"templates": ["physical", "vital", "characteristics", "animals"],
			"metaowner": {
				"type": "text",
				"dtype": "String",
				"label": "Metaowner",
				"value": "NPC"
			}
		},
		"MetaTherion": {
			"templates": ["physical", "vital", "characteristics", "animals", "entermeta"],
			"metaowner": {
				"type": "text",
				"dtype": "String",
				"label": "Metaowner",
				"value": "NPC"
			}
		},
		"Artificial": {
			"templates": ["physical", "vital", "characteristics", "synthetic"],
			"metaowner": {
				"type": "text",
				"dtype": "String",
				"label": "Metaowner",
				"value": "NPC"
			}
		},
		"Animated-Object": {
			"templates": ["physical"],
			"metaowner": {
				"type": "text",
				"dtype": "String",
				"label": "Metaowner",
				"value": "NPC"
			}
		},
		"Animated-Humanoid": {
			"templates": ["physical", "vital", "characteristics", "humanoids", "perks"],
			"metaowner": {
				"type": "text",
				"dtype": "String",
				"label": "Metaowner",
				"value": "NPC"
			}
		},
		"Vehicle": {
			"templates": ["physical", "synthetic"],
			"metaowner": {
				"type": "text",
				"dtype": "String",
				"label": "Metaowner",
				"value": "NPC"
			}
		}
	},
	"Item": {
		"types": ["Object", "Possession", "Metapower", "Combo"],
		"templates": {
			"material": {
				"Material": {
					"Category": {
						"type": "text",
						"dtype": "String",
						"label": "🧱 Category",
						"value": "Earthly, Compossed, Metallic or Alien"
					},
					"Durability": {
						"type": "number",
						"dtype": "Number",
						"label": "🧱 🤍",
						"value": "10"
					},
					"Size": {
						"type": "number",
						"dtype": "Number",
						"label": "🧱 📐",
						"value": "10"
					},
					"Weight": {
						"type": "number",
						"dtype": "Number",
						"label": "🧱 ⚖️",
						"value": "10"
					},
					"Cosmic": {
						"type": "number",
						"dtype": "Number",
						"label": "🧱 Cosmic Resistance",
						"initial": 0
					},
					"Elemental": {
						"type": "number",
						"dtype": "Number",
						"label": "🧱 Elemental Resistance",
						"initial": 0
					},
					"Material": {
						"type": "number",
						"dtype": "Number",
						"label": "🧱 Material Resistance",
						"initial": 0
					},
					"Psychic": {
						"type": "number",
						"dtype": "Number",
						"label": "🧱 Psychic Resistance",
						"initial": 0
					},
					"Description": {
						"type": "text",
						"dtype": "String",
						"label": "🧱 Description",
						"value": "some material properties"
					}
				}
			},
			"metabase": {
				"Activation": {
					"Classification": {
						"type": "text",
						"dtype": "String",
						"label": "Classification",
						"value": "example Utilitarian"
					},
					"MetapowerName": {
						"type": "text",
						"dtype": "String",
						"label": "Metapower",
						"value": "example 6th Sense"
					},
					"Level": {
						"type": "number",
						"dtype": "Number",
						"label": "⏫",
						"value": "1"
					},
					"EnergyType": {
						"type": "text",
						"dtype": "String",
						"label": "✨",
						"value": "some energy type"
					},
					"DestinyCost": {
						"type": "number",
						"dtype": "Number",
						"label": "🤞",
						"value": 0
					},
					"StatRolled": {
						"type": "text",
						"dtype": "String",
						"label": "🎲",
						"value": "Willpower"
					},
					"ActionSlot": {
						"type": "text",
						"dtype": "String",
						"label": "⏱",
						"value": "Main Action"
					},
					"Targets": {
						"type": "text",
						"dtype": "String",
						"label": "🎯",
						"value": "some targets"
					},
					"Duration": {
						"type": "text",
						"dtype": "String",
						"label": "⏳",
						"value": "some duration"
					},
					"AreaEffect": {
						"type": "text",
						"dtype": "String",
						"label": "🗺️",
						"value": "some area effect"
					},
					"Range": {
						"type": "text",
						"dtype": "String",
						"label": "📏",
						"value": "some range"
					},
					"Damage": {
						"type": "text",
						"dtype": "String",
						"label": "💥",
						"value": "some damage"
					},
					"Healing": {
						"type": "text",
						"dtype": "String",
						"label": "💞",
						"value": "some healing"
					},
					"Buffs": {
						"type": "text",
						"dtype": "String",
						"label": "🛡️",
						"value": "some buffs"
					},
					"Conditions": {
						"type": "text",
						"dtype": "String",
						"label": "💀",
						"value": "some conditions"
					},
					"Notes": {
						"type": "text",
						"dtype": "String",
						"label": "Metabase Notes",
						"value": "some metabase notes"
					}
				}
			}
		},
		"Object": {
			"templates": ["material"],
			"Description": {
				"type": "text",
				"dtype": "String",
				"label": "Object Description",
				"value": "some object description"
			}
		},
		"Possession": {
			"templates": ["material"],
			"Category": {
				"type": "text",
				"dtype": "String",
				"label": "Category",
				"value": "Weapon"
			},
			"StatRolled": {
				"type": "text",
				"dtype": "String",
				"label": "🎲",
				"value": "Creativity"
			},
			"Description": {
				"type": "text",
				"dtype": "String",
				"label": "Possession Description",
				"value": "some possession description https://content.invisioncic.com/e290497/monthly_2021_02/1243943215_RULESC3.png.28493c483d72ebeb1eec27a7b7951e7b.png"
			}
		},
		"Metapower": {
			"templates": ["metabase"],
			"Description": {
				"type": "text",
				"dtype": "String",
				"label": "Metapower Description",
				"value": "some metapower description"
			},
			"Effects": {
				"type": "text",
				"dtype": "String",
				"label": "Metapower Effects",
				"value": "some metapower effects with [[/roll 10d10x10]] roll tests"
			}
		},
		"Combo": {
			"templates": ["metabase"],
			"Description": {
				"type": "text",
				"dtype": "String",
				"label": "Combo Description",
				"value": "Combos are not officially supported yet. This is a placeholder for future capabilities."
			}
		}
	}
}
