{
  "name": "Animator",
  "sorting": "a",
  "folder": null,
  "type": "Item",
  "description": "",
  "sort": 100000,
  "color": "#eb8f0f",
  "flags": {
    "df-qol": {
      "colour": ""
    },
    "scene-packer": {
      "hash": "5ca7485bb6c92018444d1dcb4638b51e7246f2e7"
    }
  },
  "_stats": {
    "systemId": "metanthropes",
    "systemVersion": "0.8.85",
    "coreVersion": "11.315",
    "createdTime": 1693133091355,
    "modifiedTime": 1700757622476,
    "lastModifiedBy": "yjFY5zW9urDSuce5"
  },
  "_id": "cGvojzNz268Tn8A3",
  "_key": "!folders!cGvojzNz268Tn8A3"
}
